publitio/__init__.py
publitio/publitio.py
publitio-1.3.1.dist-info/LICENSE
publitio-1.3.1.dist-info/METADATA
publitio-1.3.1.dist-info/WHEEL
publitio-1.3.1.dist-info/top_level.txt
publitio-1.3.1.dist-info/RECORD
