Metadata-Version: 2.1
Name: publitio
Version: 1.3.1
Summary: A Python SDK for https://publit.io
Home-page: https://github.com/ennmichael/publitio-python-sdk
Author: Enn Michael
Author-email: enntheprogrammer@gmail.com
License: UNKNOWN
Keywords: publitio
Platform: UNKNOWN
Classifier: Programming Language :: Python :: 3
Classifier: Operating System :: OS Independent
Requires-Dist: requests
